Workbook

Sheet Cover
B3: WINGSTOP INC. (NASDAQ: WING)
B4: Discounted Cash Flow Valuation Model
B6: Prepared by: Adebola Awokoya
B7: Date: May 2026 | All figures USD millions unless noted
B13: CONTENTS
B14: ▸ Assumptions | C14: Key operating & valuation inputs
B15: ▸ Income Statement | C15: Historical FY21–FY24 + 5-yr projections
B16: ▸ FCF Build | C16: Unlevered free cash flow bridge
B17: ▸ WACC | C17: Cost of equity, debt & WACC derivation
B18: ▸ DCF Valuation | C18: Terminal value, PV of FCFs, implied price
B19: ▸ Sensitivity | C19: Share price vs WACC & growth scenarios
B22: DATA SOURCES
B23: • Wingstop 10-K FY2024 (SEC EDGAR)
B24: • Wingstop 10-K FY2023 (SEC EDGAR)
B25: • Damodaran Online — US Market Risk Premium & Beta (Jan 2026)
B26: • FRED — 10-Year US Treasury Yield (May 2026)

Sheet Assumptions
B2: MODEL ASSUMPTIONS | C2: Blue = input | Black = formula | Green = cross-sheet link
B4: A. REVENUE ASSUMPTIONS
B5: FY2025E system-wide sales growth | C5: 0.155
B6: FY2026E system-wide sales growth | C6: 0.145
B7: FY2027E system-wide sales growth | C7: 0.135
B8: FY2028E system-wide sales growth | C8: 0.125
B9: FY2029E system-wide sales growth | C9: 0.115
B11: B. MARGIN ASSUMPTIONS
B12: EBITDA margin — FY2025E | C12: 0.295
B13: EBITDA margin — FY2026E | C13: 0.305
B14: EBITDA margin — FY2027E | C14: 0.31
B15: EBITDA margin — FY2028E | C15: 0.315
B16: EBITDA margin — FY2029E | C16: 0.32
B17: D&A as % of revenue | C17: 0.033
B18: Effective tax rate | C18: 0.258
B20: C. CAPEX & WORKING CAPITAL
B21: Capex as % of revenue | C21: 0.028
B22: Change in NWC as % of Δ revenue | C22: 0.02
B24: D. WACC INPUTS
B25: Risk-free rate (10-yr UST) | C25: 0.043
B26: Equity risk premium (Damodaran) | C26: 0.046
B27: Levered beta | C27: 1.18
B28: Cost of equity [Ke = Rf + β×ERP] | C28: =C25+C27*C26 -> 0.09728
B29: Pre-tax cost of debt | C29: 0.055
B30: After-tax cost of debt | C30: =C29*(1-C18) -> 0.04081
B31: Debt weight | C31: 0.35
B32: Equity weight | C32: =1-C31 -> 0.65
B33: WACC [= Ke×We + Kd×Wd] | C33: =C28*C32+C30*C31 -> 0.0775155
B35: E. TERMINAL VALUE
B36: Terminal growth rate (g) | C36: 0.03
B37: Exit EV/EBITDA (cross-check) | C37: 25
B39: F. SHARE & BALANCE SHEET DATA
B40: Diluted shares outstanding (mm) | C40: 28.5
B41: Net debt ($mm) | C41: 316
B42: Current share price ($) — ref only | C42: 285

Sheet Income Statement
B2: INCOME STATEMENT ($mm)
C4: FY2021A | D4: FY2022A | E4: FY2023A | F4: FY2024A | G4: FY2025E | H4: FY2026E | I4: FY2027E | J4: FY2028E | K4: FY2029E
B5: REVENUE
B6: Royalties | C6: 134.1 | D6: 176.3 | E6: 220 | F6: 265.4 | G6: =G10*0.681 -> 306.67779 | H6: =H10*0.681 -> 351.14607 | I6: =I10*0.681 -> 398.55079 | J6: =J10*0.681 -> 448.36964 | K6: =K10*0.681 -> 499.93215
B7: Franchise & dev fees | C7: 6.7 | D7: 7.8 | E7: 9.2 | F7: 10.5 | G7: =G10*0.027 -> 12.159031 | H7: =H10*0.027 -> 13.922091 | I7: =I10*0.027 -> 15.801573 | J7: =J10*0.027 -> 17.77677 | K7: =K10*0.027 -> 19.821099
B8: Company-owned sales | C8: 31.2 | D8: 44.3 | E8: 52.1 | F8: 57.8 | G8: =G10*0.148 -> 66.649506 | H8: =H10*0.148 -> 76.313684 | I8: =I10*0.148 -> 86.616032 | J8: =J10*0.148 -> 97.443036 | K8: =K10*0.148 -> 108.64898
B9: Technology fees | C9: 29.5 | D9: 38 | E9: 47.5 | F9: 56.2 | G9: =G10*0.144 -> 64.848168 | H9: =H10*0.144 -> 74.251152 | I9: =I10*0.144 -> 84.275058 | J9: =J10*0.144 -> 94.80944 | K9: =K10*0.144 -> 105.71253
B10: Total Revenue | C10: 201.5 | D10: 266.4 | E10: 328.8 | F10: 389.9 | G10: =F10*(1+0.155) -> 450.3345 | H10: =G10*(1+0.145) -> 515.633 | I10: =H10*(1+0.135) -> 585.24346 | J10: =I10*(1+0.125) -> 658.39889 | K10: =J10*(1+0.115) -> 734.11476
B11: OPERATING EXPENSES
B12: COGS (company-owned) | C12: 24.2 | D12: 33.1 | E12: 38.8 | F12: 43.2 | G12: =G10*0.111 -> 49.98713 | H12: =H10*0.111 -> 57.235263 | I12: =I10*0.111 -> 64.962024 | J12: =J10*0.111 -> 73.082277 | K12: =K10*0.111 -> 81.486739
B13: SG&A | C13: 81.3 | D13: 97.4 | E13: 112.5 | F13: 129.8 | G13: =G10-G12-G14-G16 -> 267.49869 | H13: =H10-H12-H14-H16 -> 301.12967 | I13: =I10-I12-I14-I16 -> 338.85596 | J13: =J10-J12-J14-J16 -> 377.92096 | K13: =K10-K12-K14-K16 -> 417.7113
B14: Depreciation & Amort | C14: 7.4 | D14: 9.3 | E14: 10.9 | F14: 13.6 | G14: =G10*0.035 -> 15.761707 | H14: =H10*0.033 -> 17.015889 | I14: =I10*0.031 -> 18.142547 | J14: =J10*0.03 -> 19.751967 | K14: =K10*0.029 -> 21.289328
B15: Total OpEx | C15: =C12+C13+C14 -> 112.9 | D15: =D12+D13+D14 -> 139.8 | E15: =E12+E13+E14 -> 162.2 | F15: =F12+F13+F14 -> 186.6 | G15: =G12+G13+G14 -> 333.24753 | H15: =H12+H13+H14 -> 375.38083 | I15: =I12+I13+I14 -> 421.96053 | J15: =J12+J13+J14 -> 470.75521 | K15: =K12+K13+K14 -> 520.48737
B16: EBIT | C16: 88.6 | D16: 126.6 | E16: 166.6 | F16: 203.3 | G16: =G10*0.26 -> 117.08697 | H16: =H10*0.272 -> 140.25218 | I16: =I10*0.279 -> 163.28292 | J16: =J10*0.285 -> 187.64368 | K16: =K10*0.291 -> 213.6274
B17: Interest expense | C17: 18.9 | D17: 20.1 | E17: 23.4 | F17: 27.2 | G17: 28 | H17: 28.9 | I17: 29.7 | J17: 30.6 | K17: 31.5
B18: EBT | C18: =C16-C17 -> 69.7 | D18: =D16-D17 -> 106.5 | E18: =E16-E17 -> 143.2 | F18: =F16-F17 -> 176.1 | G18: =G16-G17 -> 89.08697 | H18: =H16-H17 -> 111.35218 | I18: =I16-I17 -> 133.58292 | J18: =J16-J17 -> 157.04368 | K18: =K16-K17 -> 182.1274
B19: Income taxes | C19: 17.9 | D19: 27.5 | E19: 37 | F19: 45.4 | G19: =G18*Assumptions!$C$18 -> 22.984438 | H19: =H18*Assumptions!$C$18 -> 28.728862 | I19: =I18*Assumptions!$C$18 -> 34.464395 | J19: =J18*Assumptions!$C$18 -> 40.51727 | K19: =K18*Assumptions!$C$18 -> 46.988868
B20: Net Income | C20: 51.8 | D20: 79 | E20: 106.2 | F20: 130.7 | G20: =G18-G19 -> 66.102532 | H20: =H18-H19 -> 82.623315 | I20: =I18-I19 -> 99.11853 | J20: =J18-J19 -> 116.52641 | K20: =K18-K19 -> 135.13853
B22: MARGINS
B23: EBITDA margin | C23: =IFERROR((C16+C14)/C10,"") -> 0.4764268 | D23: =IFERROR((D16+D14)/D10,"") -> 0.51013514 | E23: =IFERROR((E16+E14)/E10,"") -> 0.53984185 | F23: =IFERROR((F16+F14)/F10,"") -> 0.55629649 | G23: =IFERROR((G16+G14)/G10,"") -> 0.295 | H23: =IFERROR((H16+H14)/H10,"") -> 0.305 | I23: =IFERROR((I16+I14)/I10,"") -> 0.31 | J23: =IFERROR((J16+J14)/J10,"") -> 0.315 | K23: =IFERROR((K16+K14)/K10,"") -> 0.32
B24: EBIT margin | C24: =IFERROR(C16/C10,"") -> 0.43970223 | D24: =IFERROR(D16/D10,"") -> 0.47522523 | E24: =IFERROR(E16/E10,"") -> 0.506691 | F24: =IFERROR(F16/F10,"") -> 0.52141575 | G24: =IFERROR(G16/G10,"") -> 0.26 | H24: =IFERROR(H16/H10,"") -> 0.272 | I24: =IFERROR(I16/I10,"") -> 0.279 | J24: =IFERROR(J16/J10,"") -> 0.285 | K24: =IFERROR(K16/K10,"") -> 0.291
B25: Net margin | C25: =IFERROR(C20/C10,"") -> 0.25707196 | D25: =IFERROR(D20/D10,"") -> 0.29654655 | E25: =IFERROR(E20/E10,"") -> 0.3229927 | F25: =IFERROR(F20/F10,"") -> 0.33521416 | G25: =IFERROR(G20/G10,"") -> 0.1467854 | H25: =IFERROR(H20/H10,"") -> 0.16023667 | I25: =IFERROR(I20/I10,"") -> 0.1693629 | J25: =IFERROR(J20/J10,"") -> 0.17698452 | K25: =IFERROR(K20/K10,"") -> 0.18408365

Sheet FCF Build
B2: UNLEVERED FREE CASH FLOW BUILD ($mm)
C4: FY2025E | D4: FY2026E | E4: FY2027E | F4: FY2028E | G4: FY2029E
B5: EBIT | C5: ='Income Statement'!G16 -> 117.08697 | D5: ='Income Statement'!H16 -> 140.25218 | E5: ='Income Statement'!I16 -> 163.28292 | F5: ='Income Statement'!J16 -> 187.64368 | G5: ='Income Statement'!K16 -> 213.6274
B6: ( – ) Tax on EBIT | C6: =-'Income Statement'!G16*Assumptions!$C$18 -> -30.208438 | D6: =-'Income Statement'!H16*Assumptions!$C$18 -> -36.185062 | E6: =-'Income Statement'!I16*Assumptions!$C$18 -> -42.126995 | F6: =-'Income Statement'!J16*Assumptions!$C$18 -> -48.41207 | G6: =-'Income Statement'!K16*Assumptions!$C$18 -> -55.115868
B7: NOPAT | C7: =C5+C6 -> 86.878532 | D7: =D5+D6 -> 104.06712 | E7: =E5+E6 -> 121.15593 | F7: =F5+F6 -> 139.23161 | G7: =G5+G6 -> 158.51153
B8: ( + ) D&A | C8: ='Income Statement'!G14 -> 15.761707 | D8: ='Income Statement'!H14 -> 17.015889 | E8: ='Income Statement'!I14 -> 18.142547 | F8: ='Income Statement'!J14 -> 19.751967 | G8: ='Income Statement'!K14 -> 21.289328
B9: ( – ) Capex | C9: =-'Income Statement'!G10*0.03 -> -13.510035 | D9: =-'Income Statement'!H10*0.028 -> -14.437724 | E9: =-'Income Statement'!I10*0.027 -> -15.801573 | F9: =-'Income Statement'!J10*0.026 -> -17.118371 | G9: =-'Income Statement'!K10*0.025 -> -18.352869
B10: ( +/– ) Change in NWC | C10: =-('Income Statement'!G10-'Income Statement'!F10)*Assumptions!$C$22 -> -1.20869 | D10: =-('Income Statement'!H10-'Income Statement'!G10)*Assumptions!$C$22 -> -1.30597 | E10: =-('Income Statement'!I10-'Income Statement'!H10)*Assumptions!$C$22 -> -1.3922091 | F10: =-('Income Statement'!J10-'Income Statement'!I10)*Assumptions!$C$22 -> -1.4631086 | G10: =-('Income Statement'!K10-'Income Statement'!J10)*Assumptions!$C$22 -> -1.5143174
B11: Unlevered FCF (UFCF) | C11: =SUM(C7:C10) -> 87.921514 | D11: =SUM(D7:D10) -> 105.33931 | E11: =SUM(E7:E10) -> 122.10469 | F11: =SUM(F7:F10) -> 140.4021 | G11: =SUM(G7:G10) -> 159.93367

Sheet WACC
B2: WACC DERIVATION
B4: COST OF EQUITY (CAPM)
B5: Risk-free rate (Rf) | C5: =Assumptions!C25 -> 0.043 | D5: 10-yr UST, May 2026
B6: Equity risk premium (ERP) | C6: =Assumptions!C26 -> 0.046 | D6: Damodaran US ERP Jan 2026
B7: Levered beta (β) | C7: =Assumptions!C27 -> 1.18 | D7: 5-yr monthly vs S&P 500
B8: Cost of Equity (Ke) | C8: =Assumptions!C28 -> 0.09728 | D8: Ke = Rf + β × ERP
B10: COST OF DEBT
B11: Pre-tax cost of debt | C11: =Assumptions!C29 -> 0.055 | D11: Blended rate on term loans
B12: Tax rate | C12: =Assumptions!C18 -> 0.258
B13: After-tax cost of debt (Kd) | C13: =Assumptions!C30 -> 0.04081 | D13: Kd = Kd_pre × (1 – t)
B15: CAPITAL STRUCTURE
B16: Debt / total capital | C16: =Assumptions!C31 -> 0.35 | D16: Target leverage ~35%
B17: Equity / total capital | C17: =Assumptions!C32 -> 0.65
B19: WACC
B20: WACC | C20: =Assumptions!C33 -> 0.0775155 | D20: WACC = Ke×We + Kd×Wd

Sheet DCF Valuation
B2: DCF VALUATION ($mm except per share)
B4: STEP 1 — PRESENT VALUE OF FREE CASH FLOWS
E5: FY2025E | F5: FY2026E | G5: FY2027E | H5: FY2028E | I5: FY2029E
B6: Unlevered FCF ($mm) | E6: ='FCF Build'!C11 -> 87.921514 | F6: ='FCF Build'!D11 -> 105.33931 | G6: ='FCF Build'!E11 -> 122.10469 | H6: ='FCF Build'!F11 -> 140.4021 | I6: ='FCF Build'!G11 -> 159.93367
B7: Discount period (mid-yr) | E7: 0.5 | F7: 1.5 | G7: 2.5 | H7: 3.5 | I7: 4.5
B8: Discount factor | E8: =1/(1+Assumptions!$C$33)^E7 -> 0.96335917 | F8: =1/(1+Assumptions!$C$33)^F7 -> 0.89405598 | G8: =1/(1+Assumptions!$C$33)^G7 -> 0.82973839 | H8: =1/(1+Assumptions!$C$33)^H7 -> 0.77004775 | I8: =1/(1+Assumptions!$C$33)^I7 -> 0.71465121
B9: PV of FCF | E9: =E6*E8 -> 84.699997 | F9: =F6*F8 -> 94.17924 | G9: =G6*G8 -> 101.31495 | H9: =H6*H8 -> 108.11632 | I9: =I6*I8 -> 114.29679
B10: Sum of PV (FCFs) | C10: =SUM(E9:I9) -> 502.6073
B12: STEP 2 — TERMINAL VALUE (Gordon Growth Model)
B13: Terminal year UFCF (FY2029E) | C13: ='FCF Build'!G11 -> 159.93367
B14: Terminal growth rate (g) | C14: =Assumptions!C36 -> 0.03
B15: WACC | C15: =Assumptions!C33 -> 0.0775155
B16: Terminal Value [FCF×(1+g)/(WACC–g)] | C16: =C13*(1+C14)/(C15-C14) -> 3466.9041
B17: PV of Terminal Value | C17: =C16/(1+Assumptions!C33)^4.5 -> 2477.6272
B18: TV as % of EV (calc below) | C18: =IFERROR(C17/(C10+C17),"") -> 0.8313531
B20: STEP 3 — ENTERPRISE VALUE → EQUITY VALUE → SHARE PRICE
B21: PV of FCFs | C21: =C10 -> 502.6073
B22: ( + ) PV of Terminal Value | C22: =C17 -> 2477.6272
B23: Enterprise Value | C23: =C21+C22 -> 2980.2345
B24: ( – ) Net Debt | C24: =Assumptions!C41 -> 316
B25: Equity Value | C25: =C23-C24 -> 2664.2345
B26: Diluted shares (mm) | C26: =Assumptions!C40 -> 28.5
B27: Implied Share Price | C27: =C25/C26*1000 -> 93481.911
B28: Current Price (ref) | C28: =Assumptions!C42 -> 285
B29: Premium / (Discount) | C29: =IFERROR(C27/C28-1,"") -> 327.00671

Sheet Sensitivity
B2: SENSITIVITY ANALYSIS — Implied Share Price ($)
B4: TABLE 1 — WACC × Terminal Growth Rate
B5: WACC ↓ / TGR → | C5: 0.02 | D5: 0.025 | E5: 0.03 | F5: 0.035 | G5: 0.04
B6: 0.075 | C6: =IFERROR(('DCF Valuation'!C10*((1+Assumptions!$C$33)^2.5/(1+0.075)^2.5) + 'DCF Valuation'!C13*(1+0.02)/(0.075-0.02)/(1+0.075)^4.5 - Assumptions!$C$41) / Assumptions!$C$40 * 1000, "N/A") -> 81812.299 | D6: =IFERROR(('DCF Valuation'!C10*((1+Assumptions!$C$33)^2.5/(1+0.075)^2.5) + 'DCF Valuation'!C13*(1+0.025)/(0.075-0.025)/(1+0.075)^4.5 - Assumptions!$C$41) / Assumptions!$C$40 * 1000, "N/A") -> 89733.713 | E6: =IFERROR(('DCF Valuation'!C10*((1+Assumptions!$C$33)^2.5/(1+0.075)^2.5) + 'DCF Valuation'!C13*(1+0.03)/(0.075-0.03)/(1+0.075)^4.5 - Assumptions!$C$41) / Assumptions!$C$40 * 1000, "N/A") -> 99415.442 | F6: =IFERROR(('DCF Valuation'!C10*((1+Assumptions!$C$33)^2.5/(1+0.075)^2.5) + 'DCF Valuation'!C13*(1+0.035)/(0.075-0.035)/(1+0.075)^4.5 - Assumptions!$C$41) / Assumptions!$C$40 * 1000, "N/A") -> 111517.6 | G6: =IFERROR(('DCF Valuation'!C10*((1+Assumptions!$C$33)^2.5/(1+0.075)^2.5) + 'DCF Valuation'!C13*(1+0.04)/(0.075-0.04)/(1+0.075)^4.5 - Assumptions!$C$41) / Assumptions!$C$40 * 1000, "N/A") -> 127077.52
B7: 0.08 | C7: =IFERROR(('DCF Valuation'!C10*((1+Assumptions!$C$33)^2.5/(1+0.08)^2.5) + 'DCF Valuation'!C13*(1+0.02)/(0.08-0.02)/(1+0.08)^4.5 - Assumptions!$C$41) / Assumptions!$C$40 * 1000, "N/A") -> 73920.47 | D7: =IFERROR(('DCF Valuation'!C10*((1+Assumptions!$C$33)^2.5/(1+0.08)^2.5) + 'DCF Valuation'!C13*(1+0.025)/(0.08-0.025)/(1+0.08)^4.5 - Assumptions!$C$41) / Assumptions!$C$40 * 1000, "N/A") -> 80415.303 | E7: =IFERROR(('DCF Valuation'!C10*((1+Assumptions!$C$33)^2.5/(1+0.08)^2.5) + 'DCF Valuation'!C13*(1+0.03)/(0.08-0.03)/(1+0.08)^4.5 - Assumptions!$C$41) / Assumptions!$C$40 * 1000, "N/A") -> 88209.102 | F7: =IFERROR(('DCF Valuation'!C10*((1+Assumptions!$C$33)^2.5/(1+0.08)^2.5) + 'DCF Valuation'!C13*(1+0.035)/(0.08-0.035)/(1+0.08)^4.5 - Assumptions!$C$41) / Assumptions!$C$40 * 1000, "N/A") -> 97734.856 | G7: =IFERROR(('DCF Valuation'!C10*((1+Assumptions!$C$33)^2.5/(1+0.08)^2.5) + 'DCF Valuation'!C13*(1+0.04)/(0.08-0.04)/(1+0.08)^4.5 - Assumptions!$C$41) / Assumptions!$C$40 * 1000, "N/A") -> 109642.05
B8: 0.085 | C8: =IFERROR(('DCF Valuation'!C10*((1+Assumptions!$C$33)^2.5/(1+0.085)^2.5) + 'DCF Valuation'!C13*(1+0.02)/(0.085-0.02)/(1+0.085)^4.5 - Assumptions!$C$41) / Assumptions!$C$40 * 1000, "N/A") -> 67247.624 | D8: =IFERROR(('DCF Valuation'!C10*((1+Assumptions!$C$33)^2.5/(1+0.085)^2.5) + 'DCF Valuation'!C13*(1+0.025)/(0.085-0.025)/(1+0.085)^4.5 - Assumptions!$C$41) / Assumptions!$C$40 * 1000, "N/A") -> 72655.122 | E8: =IFERROR(('DCF Valuation'!C10*((1+Assumptions!$C$33)^2.5/(1+0.085)^2.5) + 'DCF Valuation'!C13*(1+0.03)/(0.085-0.03)/(1+0.085)^4.5 - Assumptions!$C$41) / Assumptions!$C$40 * 1000, "N/A") -> 79045.801 | F8: =IFERROR(('DCF Valuation'!C10*((1+Assumptions!$C$33)^2.5/(1+0.085)^2.5) + 'DCF Valuation'!C13*(1+0.035)/(0.085-0.035)/(1+0.085)^4.5 - Assumptions!$C$41) / Assumptions!$C$40 * 1000, "N/A") -> 86714.616 | G8: =IFERROR(('DCF Valuation'!C10*((1+Assumptions!$C$33)^2.5/(1+0.085)^2.5) + 'DCF Valuation'!C13*(1+0.04)/(0.085-0.04)/(1+0.085)^4.5 - Assumptions!$C$41) / Assumptions!$C$40 * 1000, "N/A") -> 96087.613
B9: 0.09 | C9: =IFERROR(('DCF Valuation'!C10*((1+Assumptions!$C$33)^2.5/(1+0.09)^2.5) + 'DCF Valuation'!C13*(1+0.02)/(0.09-0.02)/(1+0.09)^4.5 - Assumptions!$C$41) / Assumptions!$C$40 * 1000, "N/A") -> 61532.28 | D9: =IFERROR(('DCF Valuation'!C10*((1+Assumptions!$C$33)^2.5/(1+0.09)^2.5) + 'DCF Valuation'!C13*(1+0.025)/(0.09-0.025)/(1+0.09)^4.5 - Assumptions!$C$41) / Assumptions!$C$40 * 1000, "N/A") -> 66093.289 | E9: =IFERROR(('DCF Valuation'!C10*((1+Assumptions!$C$33)^2.5/(1+0.09)^2.5) + 'DCF Valuation'!C13*(1+0.03)/(0.09-0.03)/(1+0.09)^4.5 - Assumptions!$C$41) / Assumptions!$C$40 * 1000, "N/A") -> 71414.466 | F9: =IFERROR(('DCF Valuation'!C10*((1+Assumptions!$C$33)^2.5/(1+0.09)^2.5) + 'DCF Valuation'!C13*(1+0.035)/(0.09-0.035)/(1+0.09)^4.5 - Assumptions!$C$41) / Assumptions!$C$40 * 1000, "N/A") -> 77703.129 | G9: =IFERROR(('DCF Valuation'!C10*((1+Assumptions!$C$33)^2.5/(1+0.09)^2.5) + 'DCF Valuation'!C13*(1+0.04)/(0.09-0.04)/(1+0.09)^4.5 - Assumptions!$C$41) / Assumptions!$C$40 * 1000, "N/A") -> 85249.525
B10: 0.095 | C10: =IFERROR(('DCF Valuation'!C10*((1+Assumptions!$C$33)^2.5/(1+0.095)^2.5) + 'DCF Valuation'!C13*(1+0.02)/(0.095-0.02)/(1+0.095)^4.5 - Assumptions!$C$41) / Assumptions!$C$40 * 1000, "N/A") -> 56582.697 | D10: =IFERROR(('DCF Valuation'!C10*((1+Assumptions!$C$33)^2.5/(1+0.095)^2.5) + 'DCF Valuation'!C13*(1+0.025)/(0.095-0.025)/(1+0.095)^4.5 - Assumptions!$C$41) / Assumptions!$C$40 * 1000, "N/A") -> 60472.757 | E10: =IFERROR(('DCF Valuation'!C10*((1+Assumptions!$C$33)^2.5/(1+0.095)^2.5) + 'DCF Valuation'!C13*(1+0.03)/(0.095-0.03)/(1+0.095)^4.5 - Assumptions!$C$41) / Assumptions!$C$40 * 1000, "N/A") -> 64961.288 | F10: =IFERROR(('DCF Valuation'!C10*((1+Assumptions!$C$33)^2.5/(1+0.095)^2.5) + 'DCF Valuation'!C13*(1+0.035)/(0.095-0.035)/(1+0.095)^4.5 - Assumptions!$C$41) / Assumptions!$C$40 * 1000, "N/A") -> 70197.908 | G10: =IFERROR(('DCF Valuation'!C10*((1+Assumptions!$C$33)^2.5/(1+0.095)^2.5) + 'DCF Valuation'!C13*(1+0.04)/(0.095-0.04)/(1+0.095)^4.5 - Assumptions!$C$41) / Assumptions!$C$40 * 1000, "N/A") -> 76386.64
B11: 0.1 | C11: =IFERROR(('DCF Valuation'!C10*((1+Assumptions!$C$33)^2.5/(1+0.1)^2.5) + 'DCF Valuation'!C13*(1+0.02)/(0.1-0.02)/(1+0.1)^4.5 - Assumptions!$C$41) / Assumptions!$C$40 * 1000, "N/A") -> 52255.081 | D11: =IFERROR(('DCF Valuation'!C10*((1+Assumptions!$C$33)^2.5/(1+0.1)^2.5) + 'DCF Valuation'!C13*(1+0.025)/(0.1-0.025)/(1+0.1)^4.5 - Assumptions!$C$41) / Assumptions!$C$40 * 1000, "N/A") -> 55605.039 | E11: =IFERROR(('DCF Valuation'!C10*((1+Assumptions!$C$33)^2.5/(1+0.1)^2.5) + 'DCF Valuation'!C13*(1+0.03)/(0.1-0.03)/(1+0.1)^4.5 - Assumptions!$C$41) / Assumptions!$C$40 * 1000, "N/A") -> 59433.563 | F11: =IFERROR(('DCF Valuation'!C10*((1+Assumptions!$C$33)^2.5/(1+0.1)^2.5) + 'DCF Valuation'!C13*(1+0.035)/(0.1-0.035)/(1+0.1)^4.5 - Assumptions!$C$41) / Assumptions!$C$40 * 1000, "N/A") -> 63851.09 | G11: =IFERROR(('DCF Valuation'!C10*((1+Assumptions!$C$33)^2.5/(1+0.1)^2.5) + 'DCF Valuation'!C13*(1+0.04)/(0.1-0.04)/(1+0.1)^4.5 - Assumptions!$C$41) / Assumptions!$C$40 * 1000, "N/A") -> 69004.872
B13: ★ Highlighted cell = base case
B15: TABLE 2 — WACC × EBITDA Margin (FY2025E)
B16: WACC ↓ / EBITDA Mgn → | C16: 0.265 | D16: 0.28 | E16: 0.295 | F16: 0.31 | G16: 0.325
B17: 0.075 | C17: =IFERROR(('DCF Valuation'!C10*0.898305084745763*((1+Assumptions!$C$33)^2.5/(1+0.075)^2.5) + 'DCF Valuation'!C13*0.898305084745763*(1+Assumptions!$C$36)/(0.075-Assumptions!$C$36)/(1+0.075)^4.5 - Assumptions!$C$41) / Assumptions!$C$40 * 1000, "N/A") -> 88177.832 | D17: =IFERROR(('DCF Valuation'!C10*0.949152542372882*((1+Assumptions!$C$33)^2.5/(1+0.075)^2.5) + 'DCF Valuation'!C13*0.949152542372882*(1+Assumptions!$C$36)/(0.075-Assumptions!$C$36)/(1+0.075)^4.5 - Assumptions!$C$41) / Assumptions!$C$40 * 1000, "N/A") -> 93796.637 | E17: =IFERROR(('DCF Valuation'!C10*1*((1+Assumptions!$C$33)^2.5/(1+0.075)^2.5) + 'DCF Valuation'!C13*1*(1+Assumptions!$C$36)/(0.075-Assumptions!$C$36)/(1+0.075)^4.5 - Assumptions!$C$41) / Assumptions!$C$40 * 1000, "N/A") -> 99415.442 | F17: =IFERROR(('DCF Valuation'!C10*1.05084745762712*((1+Assumptions!$C$33)^2.5/(1+0.075)^2.5) + 'DCF Valuation'!C13*1.05084745762712*(1+Assumptions!$C$36)/(0.075-Assumptions!$C$36)/(1+0.075)^4.5 - Assumptions!$C$41) / Assumptions!$C$40 * 1000, "N/A") -> 105034.25 | G17: =IFERROR(('DCF Valuation'!C10*1.10169491525424*((1+Assumptions!$C$33)^2.5/(1+0.075)^2.5) + 'DCF Valuation'!C13*1.10169491525424*(1+Assumptions!$C$36)/(0.075-Assumptions!$C$36)/(1+0.075)^4.5 - Assumptions!$C$41) / Assumptions!$C$40 * 1000, "N/A") -> 110653.05
B18: 0.08 | C18: =IFERROR(('DCF Valuation'!C10*0.898305084745763*((1+Assumptions!$C$33)^2.5/(1+0.08)^2.5) + 'DCF Valuation'!C13*0.898305084745763*(1+Assumptions!$C$36)/(0.08-Assumptions!$C$36)/(1+0.08)^4.5 - Assumptions!$C$41) / Assumptions!$C$40 * 1000, "N/A") -> 78111.12 | D18: =IFERROR(('DCF Valuation'!C10*0.949152542372882*((1+Assumptions!$C$33)^2.5/(1+0.08)^2.5) + 'DCF Valuation'!C13*0.949152542372882*(1+Assumptions!$C$36)/(0.08-Assumptions!$C$36)/(1+0.08)^4.5 - Assumptions!$C$41) / Assumptions!$C$40 * 1000, "N/A") -> 83160.111 | E18: =IFERROR(('DCF Valuation'!C10*1*((1+Assumptions!$C$33)^2.5/(1+0.08)^2.5) + 'DCF Valuation'!C13*1*(1+Assumptions!$C$36)/(0.08-Assumptions!$C$36)/(1+0.08)^4.5 - Assumptions!$C$41) / Assumptions!$C$40 * 1000, "N/A") -> 88209.102 | F18: =IFERROR(('DCF Valuation'!C10*1.05084745762712*((1+Assumptions!$C$33)^2.5/(1+0.08)^2.5) + 'DCF Valuation'!C13*1.05084745762712*(1+Assumptions!$C$36)/(0.08-Assumptions!$C$36)/(1+0.08)^4.5 - Assumptions!$C$41) / Assumptions!$C$40 * 1000, "N/A") -> 93258.093 | G18: =IFERROR(('DCF Valuation'!C10*1.10169491525424*((1+Assumptions!$C$33)^2.5/(1+0.08)^2.5) + 'DCF Valuation'!C13*1.10169491525424*(1+Assumptions!$C$36)/(0.08-Assumptions!$C$36)/(1+0.08)^4.5 - Assumptions!$C$41) / Assumptions!$C$40 * 1000, "N/A") -> 98307.084
B19: 0.085 | C19: =IFERROR(('DCF Valuation'!C10*0.898305084745763*((1+Assumptions!$C$33)^2.5/(1+0.085)^2.5) + 'DCF Valuation'!C13*0.898305084745763*(1+Assumptions!$C$36)/(0.085-Assumptions!$C$36)/(1+0.085)^4.5 - Assumptions!$C$41) / Assumptions!$C$40 * 1000, "N/A") -> 69879.681 | D19: =IFERROR(('DCF Valuation'!C10*0.949152542372882*((1+Assumptions!$C$33)^2.5/(1+0.085)^2.5) + 'DCF Valuation'!C13*0.949152542372882*(1+Assumptions!$C$36)/(0.085-Assumptions!$C$36)/(1+0.085)^4.5 - Assumptions!$C$41) / Assumptions!$C$40 * 1000, "N/A") -> 74462.741 | E19: =IFERROR(('DCF Valuation'!C10*1*((1+Assumptions!$C$33)^2.5/(1+0.085)^2.5) + 'DCF Valuation'!C13*1*(1+Assumptions!$C$36)/(0.085-Assumptions!$C$36)/(1+0.085)^4.5 - Assumptions!$C$41) / Assumptions!$C$40 * 1000, "N/A") -> 79045.801 | F19: =IFERROR(('DCF Valuation'!C10*1.05084745762712*((1+Assumptions!$C$33)^2.5/(1+0.085)^2.5) + 'DCF Valuation'!C13*1.05084745762712*(1+Assumptions!$C$36)/(0.085-Assumptions!$C$36)/(1+0.085)^4.5 - Assumptions!$C$41) / Assumptions!$C$40 * 1000, "N/A") -> 83628.862 | G19: =IFERROR(('DCF Valuation'!C10*1.10169491525424*((1+Assumptions!$C$33)^2.5/(1+0.085)^2.5) + 'DCF Valuation'!C13*1.10169491525424*(1+Assumptions!$C$36)/(0.085-Assumptions!$C$36)/(1+0.085)^4.5 - Assumptions!$C$41) / Assumptions!$C$40 * 1000, "N/A") -> 88211.922
B20: 0.09 | C20: =IFERROR(('DCF Valuation'!C10*0.898305084745763*((1+Assumptions!$C$33)^2.5/(1+0.09)^2.5) + 'DCF Valuation'!C13*0.898305084745763*(1+Assumptions!$C$36)/(0.09-Assumptions!$C$36)/(1+0.09)^4.5 - Assumptions!$C$41) / Assumptions!$C$40 * 1000, "N/A") -> 63024.413 | D20: =IFERROR(('DCF Valuation'!C10*0.949152542372882*((1+Assumptions!$C$33)^2.5/(1+0.09)^2.5) + 'DCF Valuation'!C13*0.949152542372882*(1+Assumptions!$C$36)/(0.09-Assumptions!$C$36)/(1+0.09)^4.5 - Assumptions!$C$41) / Assumptions!$C$40 * 1000, "N/A") -> 67219.439 | E20: =IFERROR(('DCF Valuation'!C10*1*((1+Assumptions!$C$33)^2.5/(1+0.09)^2.5) + 'DCF Valuation'!C13*1*(1+Assumptions!$C$36)/(0.09-Assumptions!$C$36)/(1+0.09)^4.5 - Assumptions!$C$41) / Assumptions!$C$40 * 1000, "N/A") -> 71414.466 | F20: =IFERROR(('DCF Valuation'!C10*1.05084745762712*((1+Assumptions!$C$33)^2.5/(1+0.09)^2.5) + 'DCF Valuation'!C13*1.05084745762712*(1+Assumptions!$C$36)/(0.09-Assumptions!$C$36)/(1+0.09)^4.5 - Assumptions!$C$41) / Assumptions!$C$40 * 1000, "N/A") -> 75609.492 | G20: =IFERROR(('DCF Valuation'!C10*1.10169491525424*((1+Assumptions!$C$33)^2.5/(1+0.09)^2.5) + 'DCF Valuation'!C13*1.10169491525424*(1+Assumptions!$C$36)/(0.09-Assumptions!$C$36)/(1+0.09)^4.5 - Assumptions!$C$41) / Assumptions!$C$40 * 1000, "N/A") -> 79804.518
B21: 0.095 | C21: =IFERROR(('DCF Valuation'!C10*0.898305084745763*((1+Assumptions!$C$33)^2.5/(1+0.095)^2.5) + 'DCF Valuation'!C13*0.898305084745763*(1+Assumptions!$C$36)/(0.095-Assumptions!$C$36)/(1+0.095)^4.5 - Assumptions!$C$41) / Assumptions!$C$40 * 1000, "N/A") -> 57227.491 | D21: =IFERROR(('DCF Valuation'!C10*0.949152542372882*((1+Assumptions!$C$33)^2.5/(1+0.095)^2.5) + 'DCF Valuation'!C13*0.949152542372882*(1+Assumptions!$C$36)/(0.095-Assumptions!$C$36)/(1+0.095)^4.5 - Assumptions!$C$41) / Assumptions!$C$40 * 1000, "N/A") -> 61094.389 | E21: =IFERROR(('DCF Valuation'!C10*1*((1+Assumptions!$C$33)^2.5/(1+0.095)^2.5) + 'DCF Valuation'!C13*1*(1+Assumptions!$C$36)/(0.095-Assumptions!$C$36)/(1+0.095)^4.5 - Assumptions!$C$41) / Assumptions!$C$40 * 1000, "N/A") -> 64961.288 | F21: =IFERROR(('DCF Valuation'!C10*1.05084745762712*((1+Assumptions!$C$33)^2.5/(1+0.095)^2.5) + 'DCF Valuation'!C13*1.05084745762712*(1+Assumptions!$C$36)/(0.095-Assumptions!$C$36)/(1+0.095)^4.5 - Assumptions!$C$41) / Assumptions!$C$40 * 1000, "N/A") -> 68828.187 | G21: =IFERROR(('DCF Valuation'!C10*1.10169491525424*((1+Assumptions!$C$33)^2.5/(1+0.095)^2.5) + 'DCF Valuation'!C13*1.10169491525424*(1+Assumptions!$C$36)/(0.095-Assumptions!$C$36)/(1+0.095)^4.5 - Assumptions!$C$41) / Assumptions!$C$40 * 1000, "N/A") -> 72695.085
B22: 0.1 | C22: =IFERROR(('DCF Valuation'!C10*0.898305084745763*((1+Assumptions!$C$33)^2.5/(1+0.1)^2.5) + 'DCF Valuation'!C13*0.898305084745763*(1+Assumptions!$C$36)/(0.1-Assumptions!$C$36)/(1+0.1)^4.5 - Assumptions!$C$41) / Assumptions!$C$40 * 1000, "N/A") -> 52261.907 | D22: =IFERROR(('DCF Valuation'!C10*0.949152542372882*((1+Assumptions!$C$33)^2.5/(1+0.1)^2.5) + 'DCF Valuation'!C13*0.949152542372882*(1+Assumptions!$C$36)/(0.1-Assumptions!$C$36)/(1+0.1)^4.5 - Assumptions!$C$41) / Assumptions!$C$40 * 1000, "N/A") -> 55847.735 | E22: =IFERROR(('DCF Valuation'!C10*1*((1+Assumptions!$C$33)^2.5/(1+0.1)^2.5) + 'DCF Valuation'!C13*1*(1+Assumptions!$C$36)/(0.1-Assumptions!$C$36)/(1+0.1)^4.5 - Assumptions!$C$41) / Assumptions!$C$40 * 1000, "N/A") -> 59433.563 | F22: =IFERROR(('DCF Valuation'!C10*1.05084745762712*((1+Assumptions!$C$33)^2.5/(1+0.1)^2.5) + 'DCF Valuation'!C13*1.05084745762712*(1+Assumptions!$C$36)/(0.1-Assumptions!$C$36)/(1+0.1)^4.5 - Assumptions!$C$41) / Assumptions!$C$40 * 1000, "N/A") -> 63019.391 | G22: =IFERROR(('DCF Valuation'!C10*1.10169491525424*((1+Assumptions!$C$33)^2.5/(1+0.1)^2.5) + 'DCF Valuation'!C13*1.10169491525424*(1+Assumptions!$C$36)/(0.1-Assumptions!$C$36)/(1+0.1)^4.5 - Assumptions!$C$41) / Assumptions!$C$40 * 1000, "N/A") -> 66605.219
